{
  "kind": "collectionType",
  "collectionName": "banner_nol2trs",
  "info": {
    "singularName": "banner-nol2tr",
    "pluralName": "banner-nol2trs",
    "displayName": "Banner Nol2tr"
  },
  "options": {
    "draftAndPublish": true
  },
  "pluginOptions": {},
  "attributes": {
    "link": {
      "type": "string"
    },
    "description": {
      "type": "string"
    },
    "names": {
      "type": "json"
    },
    "subject": {
      "type": "string"
    },
    "type": {
      "type": "enumeration",
      "enum": [
        "interview",
        "newsic",
        "playlist"
      ]
    },
    "order": {
      "type": "integer"
    }
  }
}
